RUMUS_BANGUN_DATAR/__init__.py
RUMUS_BANGUN_DATAR/belah_ketupat.py
RUMUS_BANGUN_DATAR/lingkaran.py
RUMUS_BANGUN_DATAR/persegi.py
RUMUS_BANGUN_DATAR/persegi_panjang.py
RUMUS_BANGUN_DATAR/trapesium.py
rumus_bangun_datar-0.0.1.dist-info/METADATA
rumus_bangun_datar-0.0.1.dist-info/WHEEL
rumus_bangun_datar-0.0.1.dist-info/top_level.txt
rumus_bangun_datar-0.0.1.dist-info/RECORD
