Metadata-Version: 2.1
Name: rumus-bangun-datar
Version: 0.0.1
Summary: rumus bangun datar
Author: Muhammad Shobirin Halik
Author-email: <msaammss03@gmail.com>
Keywords: python,rumus bangun datar
Classifier: Programming Language :: Python :: 3
